LICENSE
MANIFEST.in
README
README.md
setup.py
apicrafter/__init__.py
apicrafter.egg-info/PKG-INFO
apicrafter.egg-info/SOURCES.txt
apicrafter.egg-info/dependency_links.txt
apicrafter.egg-info/top_level.txt