Metadata-Version: 1.1
Name: apicrafter
Version: 0.0.1.6
Summary: Helps users construct a simple HTTP API.
Home-page: https://github.com/Starfys/apicrafter
Author: Steven Sheffey
Author-email: stevensheffey4@gmail.com
License: GPLv3
Keywords: api http server
Platform: UNKNOWN
Classifier: Development Status :: 3 - Alpha
Classifier: Intended Audience :: Developers
Classifier: License :: OSI Approved :: GNU General Public License v3 or later (GPLv3+)
Classifier: Programming Language :: Python :: 3
Classifier: Programming Language :: Python :: 3.3
Classifier: Programming Language :: Python :: 3.4
Classifier: Programming Language :: Python :: 3.5
